stack_memory.v
module stack_memory (
    input clk,
    input reset,
    input push,
    input pop,
    input [7:0] data_in,
    output reg [7:0] data_out,
    output full,
    output empty,
    output [7:0] top   // PEEK
);

    reg [7:0] stack [0:7];
    reg [3:0] sp;

    assign empty = (sp == 0);
    assign full  = (sp == 8);
    assign top   = (sp > 0) ? stack[sp - 1] : 0;

    always @(posedge clk or posedge reset) begin
        if (reset) begin
            sp <= 0;
            data_out <= 0;
        end
        else begin
            if (push && !full) begin
                stack[sp] <= data_in;
                sp <= sp + 1;
            end
            else if (pop && !empty) begin
                sp <= sp - 1;
                data_out <= stack[sp - 1];
            end
        end
    end

endmodule

stack_memory_tb.v
`timescale 1ns/1ps

module stack_memory_tb;

    reg clk;
    reg reset;
    reg push;
    reg pop;
    reg [7:0] data_in;

    wire [7:0] data_out;
    wire full;
    wire empty;
    wire [7:0] top;   // PEEK

    
    stack_memory emir_stack (
        .clk(clk),
        .reset(reset),
        .push(push),
        .pop(pop),
        .data_in(data_in),
        .data_out(data_out),
        .full(full),
        .empty(empty),
        .top(top)
    );

    
    always #5 clk = ~clk;

    initial begin
        $dumpfile("stack_memory.vcd");
        $dumpvars(0, stack_memory_tb);

        clk = 0;
        reset = 1;
        push = 0;
        pop = 0;
        data_in = 0;

        #10 reset = 0;

        // PUSH 10
        #10 data_in = 8'd10; push = 1;
        #10 push = 0;

        // PUSH 20
        #10 data_in = 8'd20; push = 1;
        #10 push = 0;

        // PUSH 30
        #10 data_in = 8'd30; push = 1;
        #10 push = 0;

        // POP → 30
        #10 pop = 1;
        #10 pop = 0;

        // POP → 20
        #10 pop = 1;
        #10 pop = 0;

        // PUSH 40
        #10 data_in = 8'd40; push = 1;
        #10 push = 0;

        // POP → 40
        #10 pop = 1;
        #10 pop = 0;

        // POP → 10
        #10 pop = 1;
        #10 pop = 0;

        #20 $finish;
    end

endmodule

stack_memory.vcd
$date
	Wed May 06 03:18:49 2026
$end
$version
	Icarus Verilog
$end
$timescale
	1ps
$end
$scope module stack_memory_tb $end
$var wire 8 ! top [7:0] $end
$var wire 1 " full $end
$var wire 1 # empty $end
$var wire 8 $ data_out [7:0] $end
$var reg 1 % clk $end
$var reg 8 & data_in [7:0] $end
$var reg 1 ' pop $end
$var reg 1 ( push $end
$var reg 1 ) reset $end
$scope module emir_stack $end
$var wire 1 % clk $end
$var wire 8 * data_in [7:0] $end
$var wire 1 ' pop $end
$var wire 1 ( push $end
$var wire 1 ) reset $end
$var wire 8 + top [7:0] $end
$var wire 1 " full $end
$var wire 1 # empty $end
$var reg 8 , data_out [7:0] $end
$var reg 4 - sp [3:0] $end
$upscope $end
$upscope $end
$enddefinitions $end
$comment Show the parameter values. $end
$dumpall
$end
#0
$dumpvars
b0 -
b0 ,
b0 +
b0 *
1)
0(
0'
b0 &
0%
b0 $
1#
0"
b0 !
$end
#5000
1%
#10000
0%
0)
#15000
1%
#20000
0%
1(
b1010 &
b1010 *
#25000
b1010 !
b1010 +
0#
b1 -
1%
#30000
0%
0(
#35000
1%
#40000
0%
1(
b10100 &
b10100 *
#45000
b10100 !
b10100 +
b10 -
1%
#50000
0%
0(
#55000
1%
#60000
0%
1(
b11110 &
b11110 *
#65000
b11110 !
b11110 +
b11 -
1%
#70000
0%
0(
#75000
1%
#80000
0%
1'
#85000
b10100 !
b10100 +
b11110 $
b11110 ,
b10 -
1%
#90000
0%
0'
#95000
1%
#100000
0%
1'
#105000
b1010 !
b1010 +
b10100 $
b10100 ,
b1 -
1%
#110000
0%
0'
#115000
1%
#120000
0%
1(
b101000 &
b101000 *
#125000
b101000 !
b101000 +
b10 -
1%
#130000
0%
0(
#135000
1%
#140000
0%
1'
#145000
b1010 !
b1010 +
b101000 $
b101000 ,
b1 -
1%
#150000
0%
0'
#155000
1%
#160000
0%
1'
#165000
b0 !
b0 +
b1010 $
b1010 ,
1#
b0 -
1%
#170000
0%
0'
